Metadata-Version: 2.4
Name: tap-shopify
Version: 3.7.3
Summary: Singer.io tap for extracting Shopify data
Home-page: http://github.com/singer-io/tap-shopify
Author: Stitch
Classifier: Programming Language :: Python :: 3 :: Only
Requires-Python: >=3.5.2
License-File: LICENSE
Requires-Dist: ShopifyAPI==12.7.0
Requires-Dist: singer-python==6.1.1
Requires-Dist: graphql-core==3.2.6
Requires-Dist: requests==2.32.4
Provides-Extra: dev
Requires-Dist: pylint==3.3.6; extra == "dev"
Requires-Dist: ipdb; extra == "dev"
Requires-Dist: requests==2.32.4; extra == "dev"
Requires-Dist: nose; extra == "dev"
Dynamic: author
Dynamic: classifier
Dynamic: home-page
Dynamic: license-file
Dynamic: provides-extra
Dynamic: requires-dist
Dynamic: requires-python
Dynamic: summary
